music_metadata_extractor/__init__.py
music_metadata_extractor/config.py
music_metadata_extractor/models.py
music_metadata_extractor/resolver.py
music_metadata_extractor/songdata.py
music_metadata_extractor/spotify.py
music_metadata_extractor/utils.py
music_metadata_extractor/sources/__init__.py
music_metadata_extractor/sources/spotify/__init__.py
music_metadata_extractor/sources/spotify/core.py
music_metadata_extractor/sources/youtube/__init__.py
music_metadata_extractor/sources/youtube/core.py
music_metadata_extractor/sources/youtube/helpers.py
music_metadata_extractor/sources/youtube/scraper.py
music_metadata_extractor/sources/youtube_music/__init__.py
music_metadata_extractor/sources/youtube_music/converter.py
music_metadata_extractor-1.4.0.dist-info/LICENSE
music_metadata_extractor-1.4.0.dist-info/METADATA
music_metadata_extractor-1.4.0.dist-info/WHEEL
music_metadata_extractor-1.4.0.dist-info/entry_points.txt
music_metadata_extractor-1.4.0.dist-info/top_level.txt
music_metadata_extractor-1.4.0.dist-info/RECORD
