Metadata-Version: 2.1
Name: music-metadata-extractor
Version: 1.4.0
Summary: Fetch music metadata from common Music APIs for a variety of data sources
Home-page: https://github.com/lttkgp/metadata-extractor
Author: lttkgp
Author-email: ghostwriternr@gmail.com
License: MIT
Platform: UNKNOWN
Classifier: License :: OSI Approved :: MIT License
Classifier: Programming Language :: Python :: 3
Classifier: Programming Language :: Python :: 3.7
Requires-Dist: requests (==2.25.1)
Requires-Dist: beautifulsoup4 (==4.9.3)
Requires-Dist: google-api-python-client (==2.6.0)
Requires-Dist: pytest (==6.2.4)
Requires-Dist: python-dotenv (==0.17.1)
Requires-Dist: python-dateutil (==2.8.1)
Requires-Dist: spotipy (==2.18.0)
Requires-Dist: youtube-title-parse (==1.0.0)
Requires-Dist: lxml (==4.6.3)
